alphaquant/__init__.py
alphaquant/run_pipeline.py
alphaquant/benchm/__init__.py
alphaquant/benchm/benchmarking.py
alphaquant/benchm/ratios.py
alphaquant/benchm/sensitivity.py
alphaquant/classify/__init__.py
alphaquant/classify/classification_utils.py
alphaquant/classify/classify_fragments.py
alphaquant/classify/classify_precursors.py
alphaquant/classify/ml_info_table.py
alphaquant/classify/training_functions.py
alphaquant/cluster/__init__.py
alphaquant/cluster/cluster_ions.py
alphaquant/cluster/cluster_missingval.py
alphaquant/cluster/cluster_sorting.py
alphaquant/cluster/cluster_utils.py
alphaquant/cluster/ml_reorder.py
alphaquant/cluster/outlier_filtering.py
alphaquant/cluster/outlier_scoring.py
alphaquant/cluster/proteoform_statistics.py
alphaquant/config/__init__.py
alphaquant/config/config.py
alphaquant/config/download_links_for_testfiles_quicktest.yaml
alphaquant/config/download_links_for_testfiles_selected.yaml
alphaquant/config/quant_reader_config.yaml
alphaquant/config/quant_reader_config_lightweight.yaml
alphaquant/config/spectronaut_tableconfig_fragion.rs
alphaquant/config/spectronaut_tableconfig_precursor.rs
alphaquant/config/spectronaut_tableconfig_ptm_fragion.rs
alphaquant/config/variables.py
alphaquant/diffquant/__init__.py
alphaquant/diffquant/background_distributions.py
alphaquant/diffquant/condpair_analysis.py
alphaquant/diffquant/diff_analysis.py
alphaquant/diffquant/diffutils.py
alphaquant/diffquant/doublediff_analysis.py
alphaquant/multicond/__init__.py
alphaquant/multicond/diffresults_handling.py
alphaquant/multicond/median_condition_analysis.py
alphaquant/multicond/median_condition_creation.py
alphaquant/multicond/multicond_ptmnorm.py
alphaquant/multicond/multicond_utils.py
alphaquant/norm/__init__.py
alphaquant/norm/normalization.py
alphaquant/plotting/__init__.py
alphaquant/plotting/alphamapviz.py
alphaquant/plotting/base_functions.py
alphaquant/plotting/classify.py
alphaquant/plotting/colors.py
alphaquant/plotting/fcviz.py
alphaquant-0.3.1.dist-info/licenses/LICENSE
alphaquant-0.3.1.dist-info/METADATA
alphaquant-0.3.1.dist-info/WHEEL
alphaquant-0.3.1.dist-info/entry_points.txt
alphaquant-0.3.1.dist-info/top_level.txt
alphaquant-0.3.1.dist-info/RECORD
