Metadata-Version: 2.4
Name: alphaquant
Version: 0.3.1
Summary: An open-source Python package of the AlphaPept ecosystem
Author-email: Mann Labs <opensource@alphapept.com>
Project-URL: Repository, https://github.com/MannLabs/alphaquant
Project-URL: Issues, https://github.com/MannLabs/alphaquant/issues
Project-URL: Mann Labs Homepage, https://www.biochem.mpg.de/mann
Keywords: LFQ,label-free quantification,mass spectrometry,proteomics,bioinformatics,AlphaPept,AlphaPept ecosystem
Classifier: Development Status :: 5 - Production/Stable
Classifier: Intended Audience :: Science/Research
Classifier: License :: OSI Approved :: Apache Software License
Classifier: Operating System :: OS Independent
Classifier: Programming Language :: Python :: 3
Classifier: Topic :: Scientific/Engineering :: Bio-Informatics
Requires-Python: >=3.9
License-File: LICENSE
Requires-Dist: numpy
Requires-Dist: numba
Requires-Dist: statsmodels
Requires-Dist: pandas<3
Requires-Dist: scipy
Requires-Dist: matplotlib
Requires-Dist: seaborn
Requires-Dist: anytree
Requires-Dist: graphviz
Requires-Dist: click
Requires-Dist: lmfit
Requires-Dist: multiprocess
Requires-Dist: openpyxl
Requires-Dist: scikit-learn
Requires-Dist: alphabase
Requires-Dist: pyarrow
Provides-Extra: stable
Requires-Dist: numpy==1.26.4; extra == "stable"
Requires-Dist: numba==0.61.0; extra == "stable"
Requires-Dist: statsmodels==0.14.4; extra == "stable"
Requires-Dist: pandas==2.2.3; extra == "stable"
Requires-Dist: scipy==1.15.1; extra == "stable"
Requires-Dist: matplotlib==3.10.0; extra == "stable"
Requires-Dist: seaborn==0.13.2; extra == "stable"
Requires-Dist: anytree==2.12.1; extra == "stable"
Requires-Dist: graphviz==0.20.3; extra == "stable"
Requires-Dist: click==8.1.8; extra == "stable"
Requires-Dist: lmfit==1.3.2; extra == "stable"
Requires-Dist: multiprocess==0.70.17; extra == "stable"
Requires-Dist: openpyxl==3.1.5; extra == "stable"
Requires-Dist: scikit-learn==1.6.1; extra == "stable"
Requires-Dist: alphabase==1.6.0; extra == "stable"
Requires-Dist: pyarrow==19.0.0; extra == "stable"
Provides-Extra: gui
Requires-Dist: plotly; extra == "gui"
Requires-Dist: bokeh; extra == "gui"
Requires-Dist: panel; extra == "gui"
Requires-Dist: alphamap; extra == "gui"
Provides-Extra: gui-stable
Requires-Dist: plotly==5.24.1; extra == "gui-stable"
Requires-Dist: bokeh==3.6.2; extra == "gui-stable"
Requires-Dist: panel==1.6.0; extra == "gui-stable"
Requires-Dist: alphamap==0.2.0; extra == "gui-stable"
Provides-Extra: tests
Requires-Dist: pytest; extra == "tests"
Requires-Dist: nbmake; extra == "tests"
Requires-Dist: pytest-cov; extra == "tests"
Provides-Extra: development
Requires-Dist: bump-my-version; extra == "development"
Requires-Dist: matplotlib-venn; extra == "development"
Requires-Dist: ipykernel; extra == "development"
Requires-Dist: nbformat; extra == "development"
Requires-Dist: progressbar; extra == "development"
Requires-Dist: pytest; extra == "development"
Requires-Dist: nbmake; extra == "development"
Requires-Dist: pytest-cov; extra == "development"
Provides-Extra: dask
Requires-Dist: dask; extra == "dask"
Provides-Extra: dask-stable
Requires-Dist: dask==2025.1.0; extra == "dask-stable"
Dynamic: license-file
